mrex/__init__.py
mrex/constants.py
mrex/mrex.py
mrex-0.0.4.dist-info/LICENSE
mrex-0.0.4.dist-info/WHEEL
mrex-0.0.4.dist-info/METADATA
mrex-0.0.4.dist-info/RECORD
