Metadata-Version: 2.1
Name: mrex
Version: 0.0.4
Summary: Magic Regex
Author-email: Roi Gabay <roigby@gmail.com>
Requires-Python: >=3.9
Classifier: Programming Language :: Python :: 3
Classifier: License :: OSI Approved :: MIT License
Classifier: Operating System :: OS Independent
Requires-Dist: black ; extra == "dev"
Requires-Dist: pytest ; extra == "test"
Requires-Dist: pytest-cov ; extra == "test"
Project-URL: Bug Tracker, https://github.com/gabay/mrex/issues
Project-URL: Home, https://github.com/gabay/mrex
Provides-Extra: dev
Provides-Extra: test
